pylazaro/__init__.py
pylazaro/__main__.py
pylazaro/borrowing.py
pylazaro/classifiers.py
pylazaro/constants.py
pylazaro/lazaro.py
pylazaro/output.py
pylazaro/token.py
pylazaro/utils.py
pylazaro-1.1.21.dist-info/METADATA
pylazaro-1.1.21.dist-info/WHEEL
pylazaro-1.1.21.dist-info/top_level.txt
pylazaro-1.1.21.dist-info/RECORD
