Metadata-Version: 2.1
Name: pylazaro
Version: 1.1.21
Summary: A Python library for detecting lexical borrowings (with a focus on anglicisms in Spanish language)
Home-page: https://pylazaro.readthedocs.io/
Author: Elena Álvarez Mellado
Author-email: ealvarezmellado@gmail.com
License: MIT
Platform: UNKNOWN
Classifier: Intended Audience :: Developers
Classifier: License :: OSI Approved :: MIT License
Classifier: Programming Language :: Python :: 3.10
Requires-Dist: transformers
Requires-Dist: flair
Requires-Dist: attrs
Requires-Dist: torch
Requires-Dist: torchvision
Requires-Dist: spacy
Requires-Dist: python-crfsuite
Requires-Dist: quickvec
